hubdata/__init__.py
hubdata/app.py
hubdata/connect_hub.py
hubdata/create_hub_schema.py
hubdata/logging.py
hubdata-0.1.5.dist-info/METADATA
hubdata-0.1.5.dist-info/WHEEL
hubdata-0.1.5.dist-info/entry_points.txt
hubdata-0.1.5.dist-info/top_level.txt
hubdata-0.1.5.dist-info/RECORD
