Metadata-Version: 2.4
Name: hubdata
Version: 0.1.5
Summary: Python tools for accessing and working with hubverse Hub data
Author-email: Matthew Cornell <cornell@umass.edu>
Maintainer-email: Matthew Cornell <cornell@umass.edu>
License-Expression: MIT
Requires-Python: >=3.10
Requires-Dist: click>=8.1.8
Requires-Dist: pyarrow>=19.0.1
Requires-Dist: rich
Requires-Dist: structlog
